Metadata-Version: 1.1
Name: awss3lib
Version: 0.2.0
Summary: A library for simplifying AWS S3 access.
Home-page: https://github.com/antonybholmes/awss3lib
Author: Antony B Holmes
Author-email: antony.b.holmes@gmail.com
License: UNKNOWN
Platform: UNKNOWN
Classifier: Programming Language :: Python :: 3
Classifier: License :: OSI Approved :: MIT License
Classifier: Operating System :: OS Independent
